setup.py
prettyprint/__init__.py
prettyprint/prettyprint.py
pyprint_special.egg-info/PKG-INFO
pyprint_special.egg-info/SOURCES.txt
pyprint_special.egg-info/dependency_links.txt
pyprint_special.egg-info/top_level.txt