Metadata-Version: 2.1
Name: pyprint-special
Version: 1.0.0.0.0
Summary: pyprint-special
Home-page: https://github.com/PS218909/
Author: Piyush
Author-email: somanip409@gmail.com
License: MIT
Platform: UNKNOWN
Requires-Python: >=3.6
